{
  "schema_version": "1",
  "generated": "2026-03-06T14:36:52.551Z",
  "formula": "risk_score = RPN * (1 + coverage_gap_penalty); coverage_gap_penalty = 0.5 if missing_in_model, else 0.0",
  "risk_tiers": {
    "critical": "risk_score >= 200",
    "high": "100 <= risk_score < 200",
    "medium": "40 <= risk_score < 100",
    "low": "risk_score < 40"
  },
  "transitions": [
    {
      "state": "COLLECTING_VOTES",
      "event": "CIRCUIT_BREAK",
      "to_state": "COLLECTING_VOTES",
      "rpn": 120,
      "coverage_gap": true,
      "coverage_gap_penalty": 0.5,
      "risk_score": 180,
      "risk_tier": "high",
      "derived_from": [
        {
          "layer": "L3",
          "artifact": "reasoning/hazard-model.json",
          "ref": "hazards[id=HAZARD-COLLECTING_VOTES-CIRCUIT_BREAK]"
        },
        {
          "layer": "L2",
          "artifact": "semantics/observed-fsm.json",
          "ref": "observed_transitions.COLLECTING_VOTES.CIRCUIT_BREAK"
        }
      ]
    },
    {
      "state": "IDLE",
      "event": "CIRCUIT_BREAK",
      "to_state": "IDLE",
      "rpn": 120,
      "coverage_gap": false,
      "coverage_gap_penalty": 0,
      "risk_score": 120,
      "risk_tier": "high",
      "derived_from": [
        {
          "layer": "L3",
          "artifact": "reasoning/hazard-model.json",
          "ref": "hazards[id=HAZARD-IDLE-CIRCUIT_BREAK]"
        },
        {
          "layer": "L2",
          "artifact": "semantics/observed-fsm.json",
          "ref": "observed_transitions.IDLE.CIRCUIT_BREAK"
        }
      ]
    },
    {
      "state": "IDLE",
      "event": "DECIDE",
      "to_state": "IDLE",
      "rpn": 80,
      "coverage_gap": true,
      "coverage_gap_penalty": 0.5,
      "risk_score": 120,
      "risk_tier": "high",
      "derived_from": [
        {
          "layer": "L3",
          "artifact": "reasoning/hazard-model.json",
          "ref": "hazards[id=HAZARD-IDLE-DECIDE]"
        },
        {
          "layer": "L2",
          "artifact": "semantics/observed-fsm.json",
          "ref": "observed_transitions.IDLE.DECIDE"
        }
      ]
    },
    {
      "state": "IDLE",
      "event": "VOTES_COLLECTED",
      "to_state": "IDLE",
      "rpn": 80,
      "coverage_gap": true,
      "coverage_gap_penalty": 0.5,
      "risk_score": 120,
      "risk_tier": "high",
      "derived_from": [
        {
          "layer": "L3",
          "artifact": "reasoning/hazard-model.json",
          "ref": "hazards[id=HAZARD-IDLE-VOTES_COLLECTED]"
        },
        {
          "layer": "L2",
          "artifact": "semantics/observed-fsm.json",
          "ref": "observed_transitions.IDLE.VOTES_COLLECTED"
        }
      ]
    },
    {
      "state": "COLLECTING_VOTES",
      "event": "QUORUM_START",
      "to_state": "COLLECTING_VOTES",
      "rpn": 80,
      "coverage_gap": true,
      "coverage_gap_penalty": 0.5,
      "risk_score": 120,
      "risk_tier": "high",
      "derived_from": [
        {
          "layer": "L3",
          "artifact": "reasoning/hazard-model.json",
          "ref": "hazards[id=HAZARD-COLLECTING_VOTES-QUORUM_START]"
        },
        {
          "layer": "L2",
          "artifact": "semantics/observed-fsm.json",
          "ref": "observed_transitions.COLLECTING_VOTES.QUORUM_START"
        }
      ]
    },
    {
      "state": "COLLECTING_VOTES",
      "event": "DECIDE",
      "to_state": "COLLECTING_VOTES",
      "rpn": 80,
      "coverage_gap": true,
      "coverage_gap_penalty": 0.5,
      "risk_score": 120,
      "risk_tier": "high",
      "derived_from": [
        {
          "layer": "L3",
          "artifact": "reasoning/hazard-model.json",
          "ref": "hazards[id=HAZARD-COLLECTING_VOTES-DECIDE]"
        },
        {
          "layer": "L2",
          "artifact": "semantics/observed-fsm.json",
          "ref": "observed_transitions.COLLECTING_VOTES.DECIDE"
        }
      ]
    },
    {
      "state": "DELIBERATING",
      "event": "CIRCUIT_BREAK",
      "to_state": "DELIBERATING",
      "rpn": 72,
      "coverage_gap": true,
      "coverage_gap_penalty": 0.5,
      "risk_score": 108,
      "risk_tier": "high",
      "derived_from": [
        {
          "layer": "L3",
          "artifact": "reasoning/hazard-model.json",
          "ref": "hazards[id=HAZARD-DELIBERATING-CIRCUIT_BREAK]"
        },
        {
          "layer": "L2",
          "artifact": "semantics/observed-fsm.json",
          "ref": "observed_transitions.DELIBERATING.CIRCUIT_BREAK"
        }
      ]
    },
    {
      "state": "DELIBERATING",
      "event": "DECIDE",
      "to_state": "DECIDED",
      "rpn": 96,
      "coverage_gap": false,
      "coverage_gap_penalty": 0,
      "risk_score": 96,
      "risk_tier": "medium",
      "derived_from": [
        {
          "layer": "L3",
          "artifact": "reasoning/hazard-model.json",
          "ref": "hazards[id=HAZARD-DELIBERATING-DECIDE]"
        },
        {
          "layer": "L2",
          "artifact": "semantics/observed-fsm.json",
          "ref": "observed_transitions.DELIBERATING.DECIDE"
        }
      ]
    },
    {
      "state": "IDLE",
      "event": "QUORUM_START",
      "to_state": "COLLECTING_VOTES",
      "rpn": 80,
      "coverage_gap": false,
      "coverage_gap_penalty": 0,
      "risk_score": 80,
      "risk_tier": "medium",
      "derived_from": [
        {
          "layer": "L3",
          "artifact": "reasoning/hazard-model.json",
          "ref": "hazards[id=HAZARD-IDLE-QUORUM_START]"
        },
        {
          "layer": "L2",
          "artifact": "semantics/observed-fsm.json",
          "ref": "observed_transitions.IDLE.QUORUM_START"
        }
      ]
    },
    {
      "state": "COLLECTING_VOTES",
      "event": "VOTES_COLLECTED",
      "to_state": "DELIBERATING",
      "rpn": 72,
      "coverage_gap": false,
      "coverage_gap_penalty": 0,
      "risk_score": 72,
      "risk_tier": "medium",
      "derived_from": [
        {
          "layer": "L3",
          "artifact": "reasoning/hazard-model.json",
          "ref": "hazards[id=HAZARD-COLLECTING_VOTES-VOTES_COLLECTED]"
        },
        {
          "layer": "L2",
          "artifact": "semantics/observed-fsm.json",
          "ref": "observed_transitions.COLLECTING_VOTES.VOTES_COLLECTED"
        }
      ]
    },
    {
      "state": "DELIBERATING",
      "event": "QUORUM_START",
      "to_state": "DELIBERATING",
      "rpn": 48,
      "coverage_gap": true,
      "coverage_gap_penalty": 0.5,
      "risk_score": 72,
      "risk_tier": "medium",
      "derived_from": [
        {
          "layer": "L3",
          "artifact": "reasoning/hazard-model.json",
          "ref": "hazards[id=HAZARD-DELIBERATING-QUORUM_START]"
        },
        {
          "layer": "L2",
          "artifact": "semantics/observed-fsm.json",
          "ref": "observed_transitions.DELIBERATING.QUORUM_START"
        }
      ]
    },
    {
      "state": "DECIDED",
      "event": "DECIDE",
      "to_state": "DECIDED",
      "rpn": 40,
      "coverage_gap": true,
      "coverage_gap_penalty": 0.5,
      "risk_score": 60,
      "risk_tier": "medium",
      "derived_from": [
        {
          "layer": "L3",
          "artifact": "reasoning/hazard-model.json",
          "ref": "hazards[id=HAZARD-DECIDED-DECIDE]"
        },
        {
          "layer": "L2",
          "artifact": "semantics/observed-fsm.json",
          "ref": "observed_transitions.DECIDED.DECIDE"
        }
      ]
    },
    {
      "state": "DECIDED",
      "event": "CIRCUIT_BREAK",
      "to_state": "DECIDED",
      "rpn": 40,
      "coverage_gap": true,
      "coverage_gap_penalty": 0.5,
      "risk_score": 60,
      "risk_tier": "medium",
      "derived_from": [
        {
          "layer": "L3",
          "artifact": "reasoning/hazard-model.json",
          "ref": "hazards[id=HAZARD-DECIDED-CIRCUIT_BREAK]"
        },
        {
          "layer": "L2",
          "artifact": "semantics/observed-fsm.json",
          "ref": "observed_transitions.DECIDED.CIRCUIT_BREAK"
        }
      ]
    },
    {
      "state": "DECIDED",
      "event": "QUORUM_START",
      "to_state": "DECIDED",
      "rpn": 40,
      "coverage_gap": true,
      "coverage_gap_penalty": 0.5,
      "risk_score": 60,
      "risk_tier": "medium",
      "derived_from": [
        {
          "layer": "L3",
          "artifact": "reasoning/hazard-model.json",
          "ref": "hazards[id=HAZARD-DECIDED-QUORUM_START]"
        },
        {
          "layer": "L2",
          "artifact": "semantics/observed-fsm.json",
          "ref": "observed_transitions.DECIDED.QUORUM_START"
        }
      ]
    },
    {
      "state": "DECIDED",
      "event": "VOTES_COLLECTED",
      "to_state": "DECIDED",
      "rpn": 40,
      "coverage_gap": true,
      "coverage_gap_penalty": 0.5,
      "risk_score": 60,
      "risk_tier": "medium",
      "derived_from": [
        {
          "layer": "L3",
          "artifact": "reasoning/hazard-model.json",
          "ref": "hazards[id=HAZARD-DECIDED-VOTES_COLLECTED]"
        },
        {
          "layer": "L2",
          "artifact": "semantics/observed-fsm.json",
          "ref": "observed_transitions.DECIDED.VOTES_COLLECTED"
        }
      ]
    },
    {
      "state": "DELIBERATING",
      "event": "VOTES_COLLECTED",
      "to_state": "DELIBERATING",
      "rpn": 16,
      "coverage_gap": false,
      "coverage_gap_penalty": 0,
      "risk_score": 16,
      "risk_tier": "low",
      "derived_from": [
        {
          "layer": "L3",
          "artifact": "reasoning/hazard-model.json",
          "ref": "hazards[id=HAZARD-DELIBERATING-VOTES_COLLECTED]"
        },
        {
          "layer": "L2",
          "artifact": "semantics/observed-fsm.json",
          "ref": "observed_transitions.DELIBERATING.VOTES_COLLECTED"
        }
      ]
    }
  ],
  "summary": {
    "total": 16,
    "by_risk_tier": {
      "critical": 0,
      "high": 7,
      "medium": 8,
      "low": 1
    },
    "coverage_gap_count": 11
  }
}
