{
  "requirement_id": "STATE-02",
  "requirement_text": "State schema: `{ active, file_set[], activated_at, commit_window_snapshot[] }` — captures what triggered the breaker",
  "formal_property": {
    "name": "TypeOK",
    "model_file": ".planning/formal/tla/QGSDBreakerState.tla",
    "definition": "TypeOK ==",
    "type": "invariant"
  },
  "source_files": [
    "bin/design-impact.test.cjs",
    "bin/gate-a-grounding.cjs",
    "bin/manage-agents.test.cjs",
    "bin/assumption-register.cjs",
    "bin/telemetry-collector.cjs",
    "bin/nf-solve-ptoF-integration.test.cjs",
    "bin/aggregate-requirements.cjs",
    "bin/attribute-trace-divergence.cjs",
    "bin/check-spec-sync.cjs",
    "bin/observe-handler-prometheus.cjs",
    "bin/nForma.cjs",
    "bin/xstate-trace-walker.test.cjs",
    "bin/hazard-model.cjs",
    "bin/hazard-model.test.cjs",
    "bin/test-recipe-gen.cjs",
    "bin/failure-mode-catalog.test.cjs",
    "bin/design-impact.cjs",
    "bin/run-oscillation-tlc.cjs",
    "bin/accept-debug-invariant.test.cjs",
    "bin/security-sweep.test.cjs",
    "bin/observe-handler-grafana.test.cjs",
    "bin/validate-invariant.cjs",
    "bin/observe-handler-upstream.test.cjs",
    "bin/migrate-planning.cjs",
    "bin/read-policy.cjs",
    "bin/trace-corpus-stats.cjs",
    "bin/run-formal-verify.cjs",
    "bin/nf-solve.test.cjs",
    "bin/validate-traces.cjs",
    "bin/formal-core.cjs",
    "bin/quorum-formal-context.test.cjs",
    "bin/gate-a-grounding.test.cjs",
    "bin/quorum-formal-context.cjs",
    "bin/detect-coverage-gaps.test.cjs",
    "bin/manage-agents-core.cjs",
    "bin/gate-c-validation.cjs",
    "bin/generate-phase-spec.cjs",
    "bin/check-spec-sync.test.cjs",
    "bin/run-breaker-tlc.cjs",
    "bin/promote-gate-maturity.test.cjs",
    "bin/formal-proximity.cjs",
    "bin/instrumentation-map.test.cjs",
    "bin/git-heatmap.cjs",
    "bin/cross-layer-dashboard.test.cjs",
    "bin/run-account-manager-tlc.cjs",
    "bin/blessed-terminal.cjs",
    "bin/verify-formal-results.test.cjs",
    "bin/observe-handler-grafana.cjs",
    "bin/risk-heatmap.cjs",
    "bin/nForma.test.cjs",
    "bin/extract-annotations.cjs",
    "bin/analyze-assumptions.cjs",
    "bin/generate-proposed-changes.test.cjs",
    "bin/run-tlc.cjs",
    "bin/run-phase-tlc.test.cjs",
    "bin/count-scenarios.cjs",
    "bin/initialize-model-registry.cjs",
    "bin/model-registry.test.cjs",
    "bin/assumption-register.test.cjs",
    "bin/run-phase-tlc.cjs",
    "bin/generate-phase-spec.test.cjs",
    "bin/observe-handler-prometheus.test.cjs",
    "bin/run-account-pool-alloy.cjs",
    "bin/mismatch-register.test.cjs",
    "bin/observed-fsm.cjs",
    "bin/instrumentation-map.cjs",
    "bin/account-manager.cjs",
    "bin/check-liveness-fairness.test.cjs",
    "bin/harness-diagnostic.cjs",
    "bin/gate-c-validation.test.cjs",
    "bin/promote-model.test.cjs",
    "bin/xstate-to-tla.test.cjs",
    "bin/observe-handlers.cjs",
    "bin/validate-traces.test.cjs",
    "bin/xstate-trace-walker.cjs",
    "bin/observe-handler-upstream.cjs",
    "bin/generate-tla-cfg.cjs",
    "bin/install.js",
    "bin/generate-formal-specs.cjs",
    "bin/generate-petri-net.test.cjs",
    "bin/autoClosePtoF.cjs",
    "bin/risk-heatmap.test.cjs",
    "bin/generate-traceability-matrix.cjs",
    "bin/debt-dedup.cjs",
    "bin/attribute-trace-divergence.test.cjs",
    "bin/autoClosePtoF.test.cjs",
    "bin/run-prism.cjs",
    "bin/planning-paths.cjs",
    "bin/initialize-model-registry.test.cjs",
    "bin/failure-taxonomy.cjs",
    "bin/nf-solve.cjs",
    "bin/state-candidates.cjs",
    "bin/observe-handler-internal.cjs",
    "bin/lint-formal-models.cjs",
    "bin/nf-debt.test.cjs",
    "bin/debt-state-machine.cjs",
    "bin/oscillation-audit.test.cjs",
    "bin/test-recipe-gen.test.cjs",
    "bin/debt-state-machine.test.cjs",
    "bin/conformance-schema.test.cjs",
    "bin/quorum-cache.cjs",
    "bin/harness-diagnostic.test.cjs",
    "bin/generate-proposed-changes.cjs",
    "bin/read-policy.test.cjs",
    "bin/detect-coverage-gaps.cjs",
    "bin/xstate-to-tla.cjs",
    "bin/quorum-slot-dispatch.cjs",
    "bin/build-phase-index.cjs",
    "bin/analyze-state-space.cjs",
    "bin/validate-memory.cjs",
    "bin/observed-fsm.test.cjs",
    "bin/state-candidates.test.cjs",
    "bin/failure-mode-catalog.cjs",
    "bin/build-layer-manifest.cjs",
    "bin/analyze-assumptions.test.cjs",
    "bin/mismatch-register.cjs",
    "bin/test-formal-integration.test.cjs",
    "hooks/nf-console-guard.js",
    "hooks/nf-precompact.test.js",
    "hooks/dist/nf-console-guard.js",
    "hooks/dist/nf-precompact.test.js",
    "hooks/dist/nf-prompt.test.js",
    "hooks/dist/nf-circuit-breaker.test.js",
    "hooks/dist/nf-precompact.js",
    "hooks/dist/gsd-context-monitor.js",
    "hooks/dist/nf-session-start.js",
    "hooks/dist/nf-circuit-breaker.js",
    "hooks/dist/nf-spec-regen.js",
    "hooks/dist/nf-prompt.js",
    "hooks/nf-prompt.test.js",
    "hooks/nf-circuit-breaker.test.js",
    "hooks/nf-precompact.js",
    "hooks/gsd-context-monitor.js",
    "hooks/nf-session-start.js",
    "hooks/nf-circuit-breaker.js",
    "hooks/nf-spec-regen.js",
    "hooks/nf-prompt.js"
  ],
  "source_file_absolute": "/Users/jonathanborduas/code/QGSD/bin/design-impact.test.cjs",
  "source_files_absolute": [
    "/Users/jonathanborduas/code/QGSD/bin/design-impact.test.cjs",
    "/Users/jonathanborduas/code/QGSD/bin/gate-a-grounding.cjs",
    "/Users/jonathanborduas/code/QGSD/bin/manage-agents.test.cjs",
    "/Users/jonathanborduas/code/QGSD/bin/assumption-register.cjs",
    "/Users/jonathanborduas/code/QGSD/bin/telemetry-collector.cjs",
    "/Users/jonathanborduas/code/QGSD/bin/nf-solve-ptoF-integration.test.cjs",
    "/Users/jonathanborduas/code/QGSD/bin/aggregate-requirements.cjs",
    "/Users/jonathanborduas/code/QGSD/bin/attribute-trace-divergence.cjs",
    "/Users/jonathanborduas/code/QGSD/bin/check-spec-sync.cjs",
    "/Users/jonathanborduas/code/QGSD/bin/observe-handler-prometheus.cjs",
    "/Users/jonathanborduas/code/QGSD/bin/nForma.cjs",
    "/Users/jonathanborduas/code/QGSD/bin/xstate-trace-walker.test.cjs",
    "/Users/jonathanborduas/code/QGSD/bin/hazard-model.cjs",
    "/Users/jonathanborduas/code/QGSD/bin/hazard-model.test.cjs",
    "/Users/jonathanborduas/code/QGSD/bin/test-recipe-gen.cjs",
    "/Users/jonathanborduas/code/QGSD/bin/failure-mode-catalog.test.cjs",
    "/Users/jonathanborduas/code/QGSD/bin/design-impact.cjs",
    "/Users/jonathanborduas/code/QGSD/bin/run-oscillation-tlc.cjs",
    "/Users/jonathanborduas/code/QGSD/bin/accept-debug-invariant.test.cjs",
    "/Users/jonathanborduas/code/QGSD/bin/security-sweep.test.cjs",
    "/Users/jonathanborduas/code/QGSD/bin/observe-handler-grafana.test.cjs",
    "/Users/jonathanborduas/code/QGSD/bin/validate-invariant.cjs",
    "/Users/jonathanborduas/code/QGSD/bin/observe-handler-upstream.test.cjs",
    "/Users/jonathanborduas/code/QGSD/bin/migrate-planning.cjs",
    "/Users/jonathanborduas/code/QGSD/bin/read-policy.cjs",
    "/Users/jonathanborduas/code/QGSD/bin/trace-corpus-stats.cjs",
    "/Users/jonathanborduas/code/QGSD/bin/run-formal-verify.cjs",
    "/Users/jonathanborduas/code/QGSD/bin/nf-solve.test.cjs",
    "/Users/jonathanborduas/code/QGSD/bin/validate-traces.cjs",
    "/Users/jonathanborduas/code/QGSD/bin/formal-core.cjs",
    "/Users/jonathanborduas/code/QGSD/bin/quorum-formal-context.test.cjs",
    "/Users/jonathanborduas/code/QGSD/bin/gate-a-grounding.test.cjs",
    "/Users/jonathanborduas/code/QGSD/bin/quorum-formal-context.cjs",
    "/Users/jonathanborduas/code/QGSD/bin/detect-coverage-gaps.test.cjs",
    "/Users/jonathanborduas/code/QGSD/bin/manage-agents-core.cjs",
    "/Users/jonathanborduas/code/QGSD/bin/gate-c-validation.cjs",
    "/Users/jonathanborduas/code/QGSD/bin/generate-phase-spec.cjs",
    "/Users/jonathanborduas/code/QGSD/bin/check-spec-sync.test.cjs",
    "/Users/jonathanborduas/code/QGSD/bin/run-breaker-tlc.cjs",
    "/Users/jonathanborduas/code/QGSD/bin/promote-gate-maturity.test.cjs",
    "/Users/jonathanborduas/code/QGSD/bin/formal-proximity.cjs",
    "/Users/jonathanborduas/code/QGSD/bin/instrumentation-map.test.cjs",
    "/Users/jonathanborduas/code/QGSD/bin/git-heatmap.cjs",
    "/Users/jonathanborduas/code/QGSD/bin/cross-layer-dashboard.test.cjs",
    "/Users/jonathanborduas/code/QGSD/bin/run-account-manager-tlc.cjs",
    "/Users/jonathanborduas/code/QGSD/bin/blessed-terminal.cjs",
    "/Users/jonathanborduas/code/QGSD/bin/verify-formal-results.test.cjs",
    "/Users/jonathanborduas/code/QGSD/bin/observe-handler-grafana.cjs",
    "/Users/jonathanborduas/code/QGSD/bin/risk-heatmap.cjs",
    "/Users/jonathanborduas/code/QGSD/bin/nForma.test.cjs",
    "/Users/jonathanborduas/code/QGSD/bin/extract-annotations.cjs",
    "/Users/jonathanborduas/code/QGSD/bin/analyze-assumptions.cjs",
    "/Users/jonathanborduas/code/QGSD/bin/generate-proposed-changes.test.cjs",
    "/Users/jonathanborduas/code/QGSD/bin/run-tlc.cjs",
    "/Users/jonathanborduas/code/QGSD/bin/run-phase-tlc.test.cjs",
    "/Users/jonathanborduas/code/QGSD/bin/count-scenarios.cjs",
    "/Users/jonathanborduas/code/QGSD/bin/initialize-model-registry.cjs",
    "/Users/jonathanborduas/code/QGSD/bin/model-registry.test.cjs",
    "/Users/jonathanborduas/code/QGSD/bin/assumption-register.test.cjs",
    "/Users/jonathanborduas/code/QGSD/bin/run-phase-tlc.cjs",
    "/Users/jonathanborduas/code/QGSD/bin/generate-phase-spec.test.cjs",
    "/Users/jonathanborduas/code/QGSD/bin/observe-handler-prometheus.test.cjs",
    "/Users/jonathanborduas/code/QGSD/bin/run-account-pool-alloy.cjs",
    "/Users/jonathanborduas/code/QGSD/bin/mismatch-register.test.cjs",
    "/Users/jonathanborduas/code/QGSD/bin/observed-fsm.cjs",
    "/Users/jonathanborduas/code/QGSD/bin/instrumentation-map.cjs",
    "/Users/jonathanborduas/code/QGSD/bin/account-manager.cjs",
    "/Users/jonathanborduas/code/QGSD/bin/check-liveness-fairness.test.cjs",
    "/Users/jonathanborduas/code/QGSD/bin/harness-diagnostic.cjs",
    "/Users/jonathanborduas/code/QGSD/bin/gate-c-validation.test.cjs",
    "/Users/jonathanborduas/code/QGSD/bin/promote-model.test.cjs",
    "/Users/jonathanborduas/code/QGSD/bin/xstate-to-tla.test.cjs",
    "/Users/jonathanborduas/code/QGSD/bin/observe-handlers.cjs",
    "/Users/jonathanborduas/code/QGSD/bin/validate-traces.test.cjs",
    "/Users/jonathanborduas/code/QGSD/bin/xstate-trace-walker.cjs",
    "/Users/jonathanborduas/code/QGSD/bin/observe-handler-upstream.cjs",
    "/Users/jonathanborduas/code/QGSD/bin/generate-tla-cfg.cjs",
    "/Users/jonathanborduas/code/QGSD/bin/install.js",
    "/Users/jonathanborduas/code/QGSD/bin/generate-formal-specs.cjs",
    "/Users/jonathanborduas/code/QGSD/bin/generate-petri-net.test.cjs",
    "/Users/jonathanborduas/code/QGSD/bin/autoClosePtoF.cjs",
    "/Users/jonathanborduas/code/QGSD/bin/risk-heatmap.test.cjs",
    "/Users/jonathanborduas/code/QGSD/bin/generate-traceability-matrix.cjs",
    "/Users/jonathanborduas/code/QGSD/bin/debt-dedup.cjs",
    "/Users/jonathanborduas/code/QGSD/bin/attribute-trace-divergence.test.cjs",
    "/Users/jonathanborduas/code/QGSD/bin/autoClosePtoF.test.cjs",
    "/Users/jonathanborduas/code/QGSD/bin/run-prism.cjs",
    "/Users/jonathanborduas/code/QGSD/bin/planning-paths.cjs",
    "/Users/jonathanborduas/code/QGSD/bin/initialize-model-registry.test.cjs",
    "/Users/jonathanborduas/code/QGSD/bin/failure-taxonomy.cjs",
    "/Users/jonathanborduas/code/QGSD/bin/nf-solve.cjs",
    "/Users/jonathanborduas/code/QGSD/bin/state-candidates.cjs",
    "/Users/jonathanborduas/code/QGSD/bin/observe-handler-internal.cjs",
    "/Users/jonathanborduas/code/QGSD/bin/lint-formal-models.cjs",
    "/Users/jonathanborduas/code/QGSD/bin/nf-debt.test.cjs",
    "/Users/jonathanborduas/code/QGSD/bin/debt-state-machine.cjs",
    "/Users/jonathanborduas/code/QGSD/bin/oscillation-audit.test.cjs",
    "/Users/jonathanborduas/code/QGSD/bin/test-recipe-gen.test.cjs",
    "/Users/jonathanborduas/code/QGSD/bin/debt-state-machine.test.cjs",
    "/Users/jonathanborduas/code/QGSD/bin/conformance-schema.test.cjs",
    "/Users/jonathanborduas/code/QGSD/bin/quorum-cache.cjs",
    "/Users/jonathanborduas/code/QGSD/bin/harness-diagnostic.test.cjs",
    "/Users/jonathanborduas/code/QGSD/bin/generate-proposed-changes.cjs",
    "/Users/jonathanborduas/code/QGSD/bin/read-policy.test.cjs",
    "/Users/jonathanborduas/code/QGSD/bin/detect-coverage-gaps.cjs",
    "/Users/jonathanborduas/code/QGSD/bin/xstate-to-tla.cjs",
    "/Users/jonathanborduas/code/QGSD/bin/quorum-slot-dispatch.cjs",
    "/Users/jonathanborduas/code/QGSD/bin/build-phase-index.cjs",
    "/Users/jonathanborduas/code/QGSD/bin/analyze-state-space.cjs",
    "/Users/jonathanborduas/code/QGSD/bin/validate-memory.cjs",
    "/Users/jonathanborduas/code/QGSD/bin/observed-fsm.test.cjs",
    "/Users/jonathanborduas/code/QGSD/bin/state-candidates.test.cjs",
    "/Users/jonathanborduas/code/QGSD/bin/failure-mode-catalog.cjs",
    "/Users/jonathanborduas/code/QGSD/bin/build-layer-manifest.cjs",
    "/Users/jonathanborduas/code/QGSD/bin/analyze-assumptions.test.cjs",
    "/Users/jonathanborduas/code/QGSD/bin/mismatch-register.cjs",
    "/Users/jonathanborduas/code/QGSD/bin/test-formal-integration.test.cjs",
    "/Users/jonathanborduas/code/QGSD/hooks/nf-console-guard.js",
    "/Users/jonathanborduas/code/QGSD/hooks/nf-precompact.test.js",
    "/Users/jonathanborduas/code/QGSD/hooks/dist/nf-console-guard.js",
    "/Users/jonathanborduas/code/QGSD/hooks/dist/nf-precompact.test.js",
    "/Users/jonathanborduas/code/QGSD/hooks/dist/nf-prompt.test.js",
    "/Users/jonathanborduas/code/QGSD/hooks/dist/nf-circuit-breaker.test.js",
    "/Users/jonathanborduas/code/QGSD/hooks/dist/nf-precompact.js",
    "/Users/jonathanborduas/code/QGSD/hooks/dist/gsd-context-monitor.js",
    "/Users/jonathanborduas/code/QGSD/hooks/dist/nf-session-start.js",
    "/Users/jonathanborduas/code/QGSD/hooks/dist/nf-circuit-breaker.js",
    "/Users/jonathanborduas/code/QGSD/hooks/dist/nf-spec-regen.js",
    "/Users/jonathanborduas/code/QGSD/hooks/dist/nf-prompt.js",
    "/Users/jonathanborduas/code/QGSD/hooks/nf-prompt.test.js",
    "/Users/jonathanborduas/code/QGSD/hooks/nf-circuit-breaker.test.js",
    "/Users/jonathanborduas/code/QGSD/hooks/nf-precompact.js",
    "/Users/jonathanborduas/code/QGSD/hooks/gsd-context-monitor.js",
    "/Users/jonathanborduas/code/QGSD/hooks/nf-session-start.js",
    "/Users/jonathanborduas/code/QGSD/hooks/nf-circuit-breaker.js",
    "/Users/jonathanborduas/code/QGSD/hooks/nf-spec-regen.js",
    "/Users/jonathanborduas/code/QGSD/hooks/nf-prompt.js"
  ],
  "import_hint": "const mod = require('/Users/jonathanborduas/code/QGSD/bin/design-impact.test.cjs');",
  "test_strategy": "structural",
  "template": "source-grep",
  "template_boilerplate": "const content = fs.readFileSync(SOURCE, 'utf8');\nassert.match(content, /PATTERN/);"
}
